talan/__init__.py
talan/_alan_calc.py
talan/_alan_date.py
talan/_alan_mp4.py
talan/_alan_ohlc_fcs.py
talan/_alan_optparse.py
talan/_alan_pppscf.py
talan/_alan_rmc.py
talan/_alan_str.py
talan/alanapi.py
talan/chatgptAPI.py
talan/csv2plotj2ts.py
talan/find_recent_eps.py
talan/fredReader.py
talan/get_rq.py
talan/headline_calc.py
talan/headline_sts.py
talan/iex_peers.py
talan/lsi_daily.py
talan/macro_event_yh.py
talan/plot_templates.py
talan/prc_temp_DN.py
talan/record_hilo.py
talan/talan_wrap.py
talan/theme_list.py
talan/ticker2label.py
talan/ticker_mapping.py
talan/upd_mapping_ticker.py
talan/webReader.py
talan/yh_chart.py
talan/yh_hist_batch.py
talan/yh_predefined.py
talan-0.1.5.dist-info/METADATA
talan-0.1.5.dist-info/WHEEL
talan-0.1.5.dist-info/top_level.txt
talan-0.1.5.dist-info/RECORD
