Metadata-Version: 2.1
Name: talan
Version: 0.1.5
Summary: ('Technical ALgorithmic ANalytics',)
Home-page: https://github.com/beyondbond/talan
Author: Ted Hong
Author-email: ted@beyondbond.com
License: BSD 2-clause
Platform: UNKNOWN
Classifier: Development Status :: 1 - Planning
Classifier: Intended Audience :: Financial and Insurance Industry
Classifier: License :: OSI Approved :: BSD License
Classifier: Operating System :: POSIX :: Linux
Classifier: Programming Language :: Python :: 3
Classifier: Programming Language :: Python :: 3.5
Classifier: Programming Language :: Python :: 3.8
Requires-Dist: matplotlib
Requires-Dist: numpy
Requires-Dist: pandas
Requires-Dist: scipy
